client/__init__.py
client/add_contact.py
client/database.py
client/delete_contact.py
client/main_window.py
client/main_window_conv.py
client/start_dialog.py
client/transport.py
logs/__init__.py
logs/client_log.py
logs/server_log.py
server/__init__.py
server/add_user.py
server/config_window.py
server/core.py
server/database.py
server/main_window.py
server/remove_user.py
server/stat_window.py
shared/__init__.py
shared/descriptors.py
shared/errors.py
shared/metaclasses.py
shared/utils.py
shared/variables.py
shared/wrapper.py
gbclient-1.0.dist-info/METADATA
gbclient-1.0.dist-info/WHEEL
gbclient-1.0.dist-info/top_level.txt
gbclient-1.0.dist-info/RECORD
