Metadata-Version: 2.1
Name: gbclient
Version: 1.0
Summary: Simple client script messenger
Home-page: UNKNOWN
Author: Denis S. Davydov
Author-email: dsd@trvsarov.ru
License: open
Platform: UNKNOWN
Requires-Dist: alabaster (==0.7.12)
Requires-Dist: Babel (==2.9.1)
Requires-Dist: certifi (==2021.10.8)
Requires-Dist: charset-normalizer (==2.0.11)
Requires-Dist: crypto (==1.4.1)
Requires-Dist: docutils (==0.17.1)
Requires-Dist: greenlet (==1.1.2)
Requires-Dist: idna (==3.3)
Requires-Dist: imagesize (==1.3.0)
Requires-Dist: importlib-metadata (==4.11.1)
Requires-Dist: Jinja2 (==3.0.3)
Requires-Dist: MarkupSafe (==2.0.1)
Requires-Dist: Naked (==0.1.31)
Requires-Dist: packaging (==21.3)
Requires-Dist: pycryptodome (==3.14.1)
Requires-Dist: Pygments (==2.11.2)
Requires-Dist: pyparsing (==3.0.7)
Requires-Dist: PyQt5 (==5.15.6)
Requires-Dist: PyQt5-Qt5 (==5.15.2)
Requires-Dist: PyQt5-sip (==12.9.1)
Requires-Dist: PyQt5-stubs (==5.15.2.0)
Requires-Dist: pytz (==2021.3)
Requires-Dist: PyYAML (==6.0)
Requires-Dist: requests (==2.27.1)
Requires-Dist: shellescape (==3.8.1)
Requires-Dist: snowballstemmer (==2.2.0)
Requires-Dist: Sphinx (==4.4.0)
Requires-Dist: SQLAlchemy (==1.4.31)
Requires-Dist: urllib3 (==1.26.8)
Requires-Dist: zipp (==3.7.0)
